LICENSE.txt
setup.py
SST4.egg-info/PKG-INFO
SST4.egg-info/SOURCES.txt
SST4.egg-info/dependency_links.txt
SST4.egg-info/requires.txt
SST4.egg-info/top_level.txt
hso/__init__.py
hso/hso1.py
hso/hso2.py
hso/hso3.py
hso/hso4.py